cameo_pg2gsheet
