Metadata-Version: 2.1
Name: cameo-pg2gsheet
Version: 1.0.1
Summary: PostgreSQL table to Google sheet: 將 PostgreSQL 資料庫 Table, 資料轉出為 CSV 再匯入 Google Sheet 試算表
Home-page: https://github.com/bohachu/pg2gsheet
Author: Yi-Hao Su
Author-email: elantievs@gmail.com
License: BSD 2-clause
Classifier: Programming Language :: Python :: 3
Requires-Python: >=3.9
